<?xml version="1.0" encoding="UTF-8"?><record_update table="sys_security_acl">
    <sys_security_acl action="DELETE">
        <active>true</active>
        <admin_overrides>false</admin_overrides>
        <advanced>false</advanced>
        <applies_to/>
        <condition/>
        <decision_type>allow</decision_type>
        <description>Auto-generated by write-audit; Derived from read ACL: x_snc_airline_mission; Security Attribute: UserIsAuthenticatedAndHasRightsToRead; Roles: public (security attribute restrictions apply);</description>
        <local_or_existing>Existing</local_or_existing>
        <name>x_snc_airline_mission.*</name>
        <operation display_value="query_range">e66cf897b7300210240b06dd1e11a9fd</operation>
        <script/>
        <security_attribute display_value="UserIsAuthenticatedAndHasRightsToRead">30b1557ea3dc6210103da1fdc31e6128</security_attribute>
        <sys_class_name>sys_security_acl</sys_class_name>
        <sys_created_by>@@snc_write_audit@@</sys_created_by>
        <sys_created_on>2025-05-10 04:32:04</sys_created_on>
        <sys_id>bc91c2a5f334621048dff3d465135413</sys_id>
        <sys_mod_count>0</sys_mod_count>
        <sys_name>x_snc_airline_mission.*</sys_name>
        <sys_package display_value="Airline WORK IN PROGRESS" source="x_snc_airline">54ee8da3dbd64110b652edb305961973</sys_package>
        <sys_policy/>
        <sys_scope display_value="Airline WORK IN PROGRESS">54ee8da3dbd64110b652edb305961973</sys_scope>
        <sys_update_name>sys_security_acl_bc91c2a5f334621048dff3d465135413</sys_update_name>
        <sys_updated_by>@@snc_write_audit@@</sys_updated_by>
        <sys_updated_on>2025-05-10 04:32:04</sys_updated_on>
        <type display_value="record">record</type>
    </sys_security_acl>
<sys_update_version action="INSERT_OR_UPDATE">
        <action>DELETE</action>
        <application display_value="Airline WORK IN PROGRESS">54ee8da3dbd64110b652edb305961973</application>
        <file_path/>
        <instance_id>a8cbb5133b6b5e540fd412c5e4e45a1f</instance_id>
        <instance_name>wildyokohama</instance_name>
        <name>sys_security_acl_bc91c2a5f334621048dff3d465135413</name>
        <payload><![CDATA[<?xml version="1.0" encoding="UTF-8"?><record_update table="sys_security_acl">
    <sys_security_acl action="INSERT_OR_UPDATE">
        <active>true</active>
        <admin_overrides>false</admin_overrides>
        <advanced>false</advanced>
        <applies_to/>
        <condition/>
        <decision_type>allow</decision_type>
        <description>Auto-generated by write-audit; Derived from read ACL: x_snc_airline_mission; Security Attribute: UserIsAuthenticatedAndHasRightsToRead; Roles: public (security attribute restrictions apply);</description>
        <local_or_existing>Existing</local_or_existing>
        <name>x_snc_airline_mission.*</name>
        <operation display_value="query_range">e66cf897b7300210240b06dd1e11a9fd</operation>
        <script/>
        <security_attribute display_value="UserIsAuthenticatedAndHasRightsToRead">30b1557ea3dc6210103da1fdc31e6128</security_attribute>
        <sys_class_name>sys_security_acl</sys_class_name>
        <sys_created_by>@@snc_write_audit@@</sys_created_by>
        <sys_created_on>2025-05-10 04:32:04</sys_created_on>
        <sys_id>bc91c2a5f334621048dff3d465135413</sys_id>
        <sys_mod_count>0</sys_mod_count>
        <sys_name>x_snc_airline_mission.*</sys_name>
        <sys_package display_value="Airline WORK IN PROGRESS" source="x_snc_airline">54ee8da3dbd64110b652edb305961973</sys_package>
        <sys_policy/>
        <sys_scope display_value="Airline WORK IN PROGRESS">54ee8da3dbd64110b652edb305961973</sys_scope>
        <sys_update_name>sys_security_acl_bc91c2a5f334621048dff3d465135413</sys_update_name>
        <sys_updated_by>@@snc_write_audit@@</sys_updated_by>
        <sys_updated_on>2025-05-10 04:32:04</sys_updated_on>
        <type display_value="record">record</type>
    </sys_security_acl>
</record_update>]]></payload>
        <payload_hash>-952090951</payload_hash>
        <record_name>x_snc_airline_mission.*</record_name>
        <reverted_from/>
        <source>df2fe1fc2b63ea109083fe395e91bff5</source>
        <source_table>sys_upgrade_history</source_table>
        <state>previous</state>
        <sys_created_by>system</sys_created_by>
        <sys_created_on>2025-08-21 12:31:11</sys_created_on>
        <sys_id>cb3fa5fc2b63ea109083fe395e91bfd1</sys_id>
        <sys_mod_count>0</sys_mod_count>
        <sys_recorded_at>198cc9c9a2b0000001</sys_recorded_at>
        <sys_updated_by>system</sys_updated_by>
        <sys_updated_on>2025-08-21 12:31:11</sys_updated_on>
        <type>Access Control</type>
        <update_guid>8b3fa5fcec63ea101f091537bd21f0d1</update_guid>
        <update_guid_history>8b3fa5fcec63ea101f091537bd21f0d1:-952090951</update_guid_history>
    </sys_update_version>
    <sys_metadata_delete action="INSERT_OR_UPDATE">
        <sys_audit_delete/>
        <sys_class_name>sys_metadata_delete</sys_class_name>
        <sys_created_by>@@snc_write_audit@@</sys_created_by>
        <sys_created_on>2025-12-27 20:28:20</sys_created_on>
        <sys_db_object display_value="" name="sys_security_acl">sys_security_acl</sys_db_object>
        <sys_id>2b6deea383524dbaa586596eac41c051</sys_id>
        <sys_metadata>bc91c2a5f334621048dff3d465135413</sys_metadata>
        <sys_mod_count>0</sys_mod_count>
        <sys_name>x_snc_airline_mission.*</sys_name>
        <sys_package display_value="Airline WORK IN PROGRESS" source="x_snc_airline">54ee8da3dbd64110b652edb305961973</sys_package>
        <sys_parent display_value="x_snc_airline_mission">2a5ac1493b78ea1062bf612c95e45a1b</sys_parent>
        <sys_policy/>
        <sys_scope display_value="Airline WORK IN PROGRESS">54ee8da3dbd64110b652edb305961973</sys_scope>
        <sys_scope_delete display_value="">c6f42fe7959e4054a7cc3eae6bd19390</sys_scope_delete>
        <sys_update_name>sys_security_acl_bc91c2a5f334621048dff3d465135413</sys_update_name>
        <sys_update_version display_value="sys_security_acl_bc91c2a5f334621048dff3d465135413">cb3fa5fc2b63ea109083fe395e91bfd1</sys_update_version>
        <sys_updated_by>@@snc_write_audit@@</sys_updated_by>
        <sys_updated_on>2025-12-27 20:28:20</sys_updated_on>
    </sys_metadata_delete>
</record_update>
